Metadata-Version: 2.3
Name: diffusion_rs
Version: 0.1.0
Classifier: Programming Language :: Rust
Classifier: Programming Language :: Python :: Implementation :: CPython
Classifier: Programming Language :: Python :: Implementation :: PyPy
Classifier: License :: OSI Approved :: MIT License
Classifier: Programming Language :: Python :: 3.10
Classifier: Programming Language :: Rust
Summary: Blazingly fast inference of diffusion models.
Keywords: machine-learning
Home-Page: https://github.com/EricLBuehler/diffusion-rs
Author: Eric Buehler
License: MIT
Requires-Python: >=3.10
Project-URL: Source Code, https://github.com/EricLBuehler/diffusion-rs
